fixtures/__init__.py
fixtures/click.py
pytest_fixtures-0.1.0.dist-info/LICENSE
pytest_fixtures-0.1.0.dist-info/METADATA
pytest_fixtures-0.1.0.dist-info/WHEEL
pytest_fixtures-0.1.0.dist-info/entry_points.txt
pytest_fixtures-0.1.0.dist-info/top_level.txt
pytest_fixtures-0.1.0.dist-info/RECORD
